shiller_data_processing/__init__.py
shiller_data_processing/data_extraction.py
shiller_data_processing/dataframe_manipulations.py
shiller_data_processing/shiller_header_constants.py
shiller_data_processing-0.0.10.dist-info/LICENSE
shiller_data_processing-0.0.10.dist-info/METADATA
shiller_data_processing-0.0.10.dist-info/WHEEL
shiller_data_processing-0.0.10.dist-info/top_level.txt
shiller_data_processing-0.0.10.dist-info/RECORD
