Metadata-Version: 2.1
Name: shiller_data_processing
Version: 0.0.10
Summary: A small package to help with processing the public Shiller dataset.
Author-email: Kristopher O'Sullivan <kristopher.osullivan2@gmail.com>
Project-URL: Homepage, https://github.com/Kris-os/Shiller-data-processing
Project-URL: Issues, https://github.com/Kris-os/Shiller-data-processing/issues
Classifier: Programming Language :: Python :: 3
Classifier: License :: OSI Approved :: MIT License
Classifier: Operating System :: OS Independent
Requires-Python: >=3.8
License-File: LICENSE
